jinjarecurse/main.py
jinjarecurse-0.0.3.dist-info/LICENSE
jinjarecurse-0.0.3.dist-info/METADATA
jinjarecurse-0.0.3.dist-info/WHEEL
jinjarecurse-0.0.3.dist-info/entry_points.txt
jinjarecurse-0.0.3.dist-info/top_level.txt
jinjarecurse-0.0.3.dist-info/RECORD
