Metadata-Version: 2.1
Name: jinjarecurse
Version: 0.0.3
Summary: Jinja Recursive Templating from the CLI
Home-page: https://github.com/diginc/Jinja-Recurse
Author: diginc
Author-email: adam@diginc.us
License: MIT
Keywords: jinja templater
Platform: UNKNOWN
Classifier: Development Status :: 3 - Alpha
Classifier: Topic :: Utilities
Classifier: License :: OSI Approved :: MIT License
Requires-Dist: docopt (==0.6.2)
Requires-Dist: jinja2 (==2.11.3)
Requires-Dist: markupsafe (==1.1.1)
Requires-Dist: pathlib2 (==2.3.5)
Requires-Dist: pyyaml (==5.4)
Requires-Dist: six (==1.15.0)
